AUTHORS
LICENSE
MANIFEST.in
README.rst
setup.py
django_threatmetrix.egg-info/PKG-INFO
django_threatmetrix.egg-info/SOURCES.txt
django_threatmetrix.egg-info/dependency_links.txt
django_threatmetrix.egg-info/top_level.txt
threatmetrix/__init__.py
threatmetrix/models.py
threatmetrix/urls.py
threatmetrix/views.py
threatmetrix/templates/threatmetrix/threatmetrix_js_tag.html
threatmetrix/templatetags/__init__.py
threatmetrix/templatetags/threatmetrix.py
threatmetrix/tests/__init__.py
threatmetrix/tests/settings.py
threatmetrix/tests/threatmetrix.py