Metadata-Version: 1.0
Name: django-threatmetrix
Version: 0.0.1
Summary: Django App for adding the threatmetrix script tag
Home-page: https://github.com/CashStar/django-threatmetrix
Author: CashStar
Author-email: developers@cashstar.com
License: UNKNOWN
Platform: UNKNOWN
Classifier: Programming Language :: Python
Classifier: Framework :: Django
Classifier: Intended Audience :: Developers
Classifier: Operating System :: OS Independent
Classifier: Topic :: Software Development :: Libraries :: Python Modules
Classifier: Topic :: Utilities
